<?xml version="1.0" encoding="UTF-8"?>
<!-- Created with TexturePacker http://www.codeandweb.com/texturepacker-->
<!-- $TexturePacker:SmartUpdate:4e1c67982b8394cc7cd4876f41333586$ -->
<TextureAtlas imagePath="general.png">
    <SubTexture name="A/B/1" x="312" y="175" width="60" height="60"/>
    <SubTexture name="A/B/2" x="250" y="175" width="60" height="60"/>
    <SubTexture name="A/B/3" x="418" y="234" width="42" height="44" frameX="-9" frameY="-8" frameWidth="60" frameHeight="60"/>
    <SubTexture name="A/B/4" x="188" y="175" width="60" height="60"/>
    <SubTexture name="A/N/1" x="126" y="118" width="60" height="60"/>
    <SubTexture name="A/N/2" x="64" y="118" width="60" height="60"/>
    <SubTexture name="A/N/3" x="374" y="210" width="42" height="44" frameX="-9" frameY="-8" frameWidth="60" frameHeight="60"/>
    <SubTexture name="A/N/4" x="2" y="118" width="60" height="60"/>
    <SubTexture name="A/R/1" x="436" y="126" width="60" height="60"/>
    <SubTexture name="A/R/2" x="374" y="126" width="60" height="60"/>
    <SubTexture name="A/R/3" x="429" y="188" width="42" height="44" frameX="-9" frameY="-8" frameWidth="60" frameHeight="60"/>
    <SubTexture name="A/R/4" x="312" y="113" width="60" height="60"/>
    <SubTexture name="blue" x="505" y="2" width="5" height="5"/>
    <SubTexture name="level_1" x="2" y="2" width="184" height="114"/>
    <SubTexture name="main" x="188" y="2" width="184" height="109"/>
    <SubTexture name="metal1" x="2" y="260" width="38" height="38"/>
    <SubTexture name="metalMinus" x="2" y="314" width="38" height="38"/>
    <SubTexture name="metalPlus" x="122" y="220" width="38" height="38"/>
    <SubTexture name="p1" x="250" y="113" width="60" height="60"/>
    <SubTexture name="p1n" x="188" y="113" width="60" height="60"/>
    <SubTexture name="p1p" x="436" y="64" width="60" height="60"/>
    <SubTexture name="p2" x="374" y="64" width="60" height="60"/>
    <SubTexture name="p2n" x="436" y="2" width="60" height="60"/>
    <SubTexture name="p2p" x="374" y="2" width="60" height="60"/>
    <SubTexture name="red" x="498" y="2" width="5" height="5"/>
    <SubTexture name="shadow" x="374" y="188" width="53" height="20"/>
    <SubTexture name="wood1" x="82" y="220" width="38" height="38"/>
    <SubTexture name="wood2" x="42" y="220" width="38" height="38"/>
    <SubTexture name="wood3" x="2" y="220" width="38" height="38"/>
    <SubTexture name="wood4" x="122" y="180" width="38" height="38"/>
    <SubTexture name="wood5" x="82" y="180" width="38" height="38"/>
    <SubTexture name="wood6" x="42" y="180" width="38" height="38"/>
    <SubTexture name="wood7" x="2" y="180" width="38" height="38"/>
    <SubTexture name="wood8" x="462" y="274" width="38" height="38"/>
    <SubTexture name="wood9" x="462" y="234" width="38" height="38"/>
</TextureAtlas>
